generated/__init__.py
generated/greeter_pb2.py
generated/greeter_pb2_grpc.py
generated/market_stream_pb2.py
generated/market_stream_pb2_grpc.py
helper/__init__.py
helper/logger.py
market_stream/__init__.py
market_stream/greeter_client.py
market_stream/market_stream_client.py
market_stream-0.0.5.dist-info/METADATA
market_stream-0.0.5.dist-info/WHEEL
market_stream-0.0.5.dist-info/top_level.txt
market_stream-0.0.5.dist-info/RECORD
